{
  "parent": "minecraft:recipes/root",
  "criteria": {
    "has_the_recipe": {
      "conditions": {
        "recipe": "simplegear:tin_arrow_from_regular"
      },
      "trigger": "minecraft:recipe_unlocked"
    },
    "has_tin_ingot": {
      "conditions": {
        "items": [
          {
            "tag": "forge:ingots/tin"
          }
        ]
      },
      "trigger": "minecraft:inventory_changed"
    }
  },
  "requirements": [
    [
      "has_the_recipe",
      "has_tin_ingot"
    ]
  ],
  "rewards": {
    "recipes": [
      "simplegear:tin_arrow_from_regular"
    ]
  },
  "sends_telemetry_event": false
}